abcpy/__init__.py
abcpy/acceptedparametersmanager.py
abcpy/approx_lhd.py
abcpy/continuousmodels.py
abcpy/discretemodels.py
abcpy/distances.py
abcpy/graphtools.py
abcpy/inferences.py
abcpy/jointapprox_lhd.py
abcpy/jointdistances.py
abcpy/modelselections.py
abcpy/output.py
abcpy/perturbationkernel.py
abcpy/probabilisticmodels.py
abcpy/statistics.py
abcpy/statisticslearning.py
abcpy/transformers.py
abcpy/utils.py
abcpy/NN_utilities/__init__.py
abcpy/NN_utilities/algorithms.py
abcpy/NN_utilities/datasets.py
abcpy/NN_utilities/losses.py
abcpy/NN_utilities/networks.py
abcpy/NN_utilities/trainer.py
abcpy/NN_utilities/utilities.py
abcpy/backends/__init__.py
abcpy/backends/base.py
abcpy/backends/mpi.py
abcpy/backends/mpimanager.py
abcpy/backends/spark.py
tests/NN_utilities_networks_tests.py
tests/NN_utilities_utilities_tests.py
tests/__init__.py
tests/acceptedparametersmanager_tests.py
tests/approx_lhd_tests.py
tests/backend_tests_mpi.py
tests/backend_tests_mpi_model_mpi.py
tests/continuousmodels_tests.py
tests/discretemodels_tests.py
tests/distances_tests.py
tests/graphtools_tests.py
tests/inferences_tests.py
tests/jointapprox_lhd_tests.py
tests/jointdistances_tests.py
tests/modelselections_tests.py
tests/output_tests.py
tests/perturbationkernel_tests.py
tests/pickle_tests.py
tests/probabilisticmodels_tests.py
tests/statistics_tests.py
tests/statisticslearning_tests.py
tests/test_examples.py
tests/test_examples_mpi.py
tests/transformers_tests.py
abcpy-0.6.3.dist-info/LICENSE
abcpy-0.6.3.dist-info/METADATA
abcpy-0.6.3.dist-info/WHEEL
abcpy-0.6.3.dist-info/top_level.txt
abcpy-0.6.3.dist-info/RECORD
