Metadata-Version: 2.1
Name: abcpy
Version: 0.6.3
Summary: A framework for approximate Bayesian computation (ABC) that speeds up inference by parallelizing computation on single computers or whole clusters.
Home-page: https://github.com/eth-cscs/abcpy
Author: The abcpy authors
Author-email: 
License: BSD-3
Download-URL: https://github.com/eth-cscs/abcpy/archive/v0.6.3.tar.gz
Keywords: abcpy
Platform: UNKNOWN
Classifier: Development Status :: 4 - Beta
Classifier: Programming Language :: Python :: 3
Classifier: Programming Language :: Python :: 3.6
Classifier: Programming Language :: Python :: 3.7
Classifier: Programming Language :: Python :: 3.8
Classifier: Programming Language :: Python :: 3.9
License-File: LICENSE
Requires-Dist: scipy
Requires-Dist: scikit-learn (>=0.23.1)
Requires-Dist: glmnet (>=2.2.1)
Requires-Dist: sklearn
Requires-Dist: sphinx
Requires-Dist: sphinx-rtd-theme
Requires-Dist: coverage
Requires-Dist: mpi4py
Requires-Dist: cloudpickle
Requires-Dist: matplotlib
Requires-Dist: tqdm
Requires-Dist: pot
